register/register.v
module register(clock, enable, in_reg, out_reg);
    input clock, enable;
    input   [31:0] in_reg;
    output reg [31:0] out_reg;

    always@(posedge clock)
            if(enable)
                out_reg = in_reg;
endmodule

register/register_test.v
`include "register.v"

module register_test;
    reg clock, enable;
    reg [31:0] indata;
    wire [31:0] outdata;

    register R(clock, enable, indata, outdata);

    initial
        begin
            $dumpfile("register_test.vcd");
            $dumpvars(0, register_test);
        end
        
    initial
        begin
            $display("");
            $display("clock    enableW        data_in                                    data_out                                    time");
            $monitor("  %b        %b        %b       %b  %d", clock, enable, indata, outdata, $time);
        end

    initial fork
        enable = 0;
        indata = 32'b0000_0000_0000_0000_0000_0000_0000_0000;
        #20 enable = 1;
        #30 indata = 32'b0000_0000_0000_0000_0000_0000_0000_0001;
        #40 indata = 32'b0000_0000_0000_0000_0000_0000_0000_1111;
        #60 indata = 32'b0000_0000_0000_0000_0000_0000_0001_000;
        #70 indata = 32'b0000_0000_0000_0000_0000_0000_0000_0010;
        
        #90 indata = 32'b0000_0000_0000_0000_0000_0000_1111_0000;
       
        #120 enable = 0;
        #120 indata = 32'b0000_0000_0000_0000_0000_0000_0000_0000;

        #130 enable = 1;
        #130 indata = 32'b0000_0000_0000_0000_0000_0000_0000_0011;
        #140 indata = 32'b1111_0000_0000_0000_0000_0000_0000_1111;
        #150 indata = 32'b0000_0000_0000_0000_1111_0000_0000_0000;
    join

    initial begin
        clock = 1'b0;
        forever #10 clock = ~clock;
    end

    initial #150 $finish;
    // initial #300 $finish;

endmodule

register/register_test.vcd
$date
	Sat Mar 11 07:30:23 2023
$end
$version
	Icarus Verilog
$end
$timescale
	1s
$end
$scope module register_test $end
$var wire 32 ! outdata [31:0] $end
$var reg 1 " clock $end
$var reg 1 # enable $end
$var reg 32 $ indata [31:0] $end
$scope module R $end
$var wire 1 % clock $end
$var wire 1 & enable $end
$var wire 32 ' in_reg [31:0] $end
$var reg 32 ( out_reg [31:0] $end
$upscope $end
$upscope $end
$enddefinitions $end
#0
$dumpvars
bx (
b0 '
0&
0%
b0 $
0#
0"
bx !
$end
#10
1"
1%
#20
0"
0%
1#
1&
#30
b1 (
b1 !
1"
1%
b1 $
b1 '
#40
0"
0%
b1111 $
b1111 '
#50
b1111 (
b1111 !
1"
1%
#60
0"
0%
b1000 $
b1000 '
#70
b10 (
b10 !
1"
1%
b10 $
b10 '
#80
0"
0%
#90
b11110000 (
b11110000 !
1"
1%
b11110000 $
b11110000 '
#100
0"
0%
#110
1"
1%
#120
0"
0%
0#
0&
b0 $
b0 '
#130
b11 (
b11 !
1"
1%
1#
1&
b11 $
b11 '
#140
0"
0%
b11110000000000000000000000001111 $
b11110000000000000000000000001111 '
#150
b1111000000000000 (
b1111000000000000 !
1"
1%
b1111000000000000 $
b1111000000000000 '
