decoder5to32/decoder5to32.v

module decoder5to32(enable, select, out_add);
    input           enable;
    input   [4:0]   select;
    output reg [31:0]  out_add;
 
always @(*) 
    begin
    if (enable) 
        begin
            case(select)
                5'b00000: out_add = 32'b0000_0000_0000_0000_0000_0000_0000_0001;
                5'b00001: out_add = 32'b0000_0000_0000_0000_0000_0000_0000_0010;
                5'b00010: out_add = 32'b0000_0000_0000_0000_0000_0000_0000_0100;
                5'b00011: out_add = 32'b0000_0000_0000_0000_0000_0000_0000_1000;
                5'b00100: out_add = 32'b0000_0000_0000_0000_0000_0000_0001_0000;
                5'b00101: out_add = 32'b0000_0000_0000_0000_0000_0000_0010_0000;
                5'b00110: out_add = 32'b0000_0000_0000_0000_0000_0000_0100_0000;
                5'b00111: out_add = 32'b0000_0000_0000_0000_0000_0000_1000_0000;
                5'b01000: out_add = 32'b0000_0000_0000_0000_0000_0001_0000_0000;
                5'b01001: out_add = 32'b0000_0000_0000_0000_0000_0010_0000_0000;
                5'b01010: out_add = 32'b0000_0000_0000_0000_0000_0100_0000_0000;
                5'b01011: out_add = 32'b0000_0000_0000_0000_0000_1000_0000_0000;
                5'b01100: out_add = 32'b0000_0000_0000_0000_0001_0000_0000_0000;
                5'b01101: out_add = 32'b0000_0000_0000_0000_0010_0000_0000_0000;
                5'b01110: out_add = 32'b0000_0000_0000_0000_0100_0000_0000_0000;
                5'b01111: out_add = 32'b0000_0000_0000_0000_1000_0000_0000_0000;
                
                5'b10000: out_add = 32'b0000_0000_0000_0001_0000_0000_0000_0000;
                5'b10001: out_add = 32'b0000_0000_0000_0010_0000_0000_0000_0000;
                5'b10010: out_add = 32'b0000_0000_0000_0100_0000_0000_0000_0000;
                5'b10011: out_add = 32'b0000_0000_0000_1000_0000_0000_0000_0000;
                5'b10100: out_add = 32'b0000_0000_0001_0000_0000_0000_0000_0000;
                5'b10101: out_add = 32'b0000_0000_0010_0000_0000_0000_0000_0000;
                5'b10110: out_add = 32'b0000_0000_0100_0000_0000_0000_0000_0000;
                5'b10111: out_add = 32'b0000_0000_1000_0000_0000_0000_0000_0000;
                5'b11000: out_add = 32'b0000_0001_0000_0000_0000_0000_0000_0000;
                5'b11001: out_add = 32'b0000_0010_0000_0000_0000_0000_0000_0000;
                5'b11010: out_add = 32'b0000_0100_0000_0000_0000_0000_0000_0000;
                5'b11011: out_add = 32'b0000_1000_0000_0000_0000_0000_0000_0000;
                5'b11100: out_add = 32'b0001_0000_0000_0000_0000_0000_0000_0000;
                5'b11101: out_add = 32'b0010_0000_0000_0000_0000_0000_0000_0000;
                5'b11110: out_add = 32'b0100_0000_0000_0000_0000_0000_0000_0000;
                5'b11111: out_add = 32'b1000_0000_0000_0000_0000_0000_0000_0000;
            endcase
        end
    else
        out_add = 32'b0000_0000_0000_0000_0000_0000_0000_0000;
    end

endmodule

decoder5to32/decoder5to32_test.v
`include "decoder5to32.v"

module decoder5to32_test;
    
    reg clock, enable;
    reg  [4:0]  select;   
    wire [31:0]  out_data;
    reg [31:0]  out_reg;


    decoder5to32 D0 (enable, select, out_data);

    initial
        begin
            $dumpfile("decoder5to32_test.vcd");
            $dumpvars(0, decoder5to32_test);
        end
        
    initial
        begin
            $display("");
            $display("clock     enable     select       out_data                                          time");
            $monitor("  %b        %b        %b        %b        %d", clock, enable, select, out_data, $time);
        end

    initial begin
        //when enable = 0, output is default 32'b0000
        // #0 enable = 0;

        //output is expect
        #0 enable = 1;

        #0 select = 5'b00000;         
        #10 select = 5'b00001;          
        #20 select = 5'b00010;          
        #30 select = 5'b00011;          
        #40 select = 5'b00100;                   
        #50 select = 5'b00101;          
        #60 select = 5'b00110;         
        #70 select = 5'b00111; 

        // #70 enable = 1; 
        #80 select = 5'b01000;          
        #90 select = 5'b01001;          
        #100 select = 5'b01010;         

        #110 select = 5'b01011;          
        #120 select = 5'b01100;          
        #130 select = 5'b01101;          
        #140 select = 5'b01110;          
        #150 select = 5'b01111; 
        
        // #160 enable = 0;
        #160 select = 5'b10000;        
        #170 select = 5'b10001;       
        #180 select = 5'b10010;      
        #190 select = 5'b10011;     
        #200 select = 5'b10100;    

        // #210 enable = 1; 
        #210 select = 5'b10101;   
        #220 select = 5'b10110;  
        #230 select = 5'b10111; 
        #240 select = 5'b11000;
        #250 select = 5'b11001;
        #260 select = 5'b11010;
        #270 select = 5'b11011;
        #280 select = 5'b11100;
        #290 select = 5'b11101;
        #300 select = 5'b11110;
        #310 select = 5'b11111;

        //for debugging
        //case default ==> 32'b0000 output
        // #320 select = 33; //==> carry out most signf, and show less signf bit output = 2

    end

    initial begin
        clock = 1'b0;
        forever #100 clock = ~clock;
    end

    initial #5300 $finish;

endmodule

decoder5to32/decoder5to32_test.vcd
$date
	Sat Mar 11 07:20:53 2023
$end
$version
	Icarus Verilog
$end
$timescale
	1s
$end
$scope module decoder5to32_test $end
$var wire 32 ! out_data [31:0] $end
$var reg 1 " clock $end
$var reg 1 # enable $end
$var reg 5 $ select [4:0] $end
$scope module D0 $end
$var wire 1 % enable $end
$var wire 5 & select [4:0] $end
$var reg 32 ' out_add [31:0] $end
$upscope $end
$upscope $end
$enddefinitions $end
#0
$dumpvars
b1 '
b0 &
1%
b0 $
1#
0"
b1 !
$end
#10
b10 '
b10 !
b1 $
b1 &
#30
b100 '
b100 !
b10 $
b10 &
#60
b1000 '
b1000 !
b11 $
b11 &
#100
b10000 '
b10000 !
b100 $
b100 &
1"
#150
b100000 '
b100000 !
b101 $
b101 &
#200
0"
#210
b1000000 '
b1000000 !
b110 $
b110 &
#280
b10000000 '
b10000000 !
b111 $
b111 &
#300
1"
#360
b100000000 '
b100000000 !
b1000 $
b1000 &
#400
0"
#450
b1000000000 '
b1000000000 !
b1001 $
b1001 &
#500
1"
#550
b10000000000 '
b10000000000 !
b1010 $
b1010 &
#600
0"
#660
b100000000000 '
b100000000000 !
b1011 $
b1011 &
#700
1"
#780
b1000000000000 '
b1000000000000 !
b1100 $
b1100 &
#800
0"
#900
1"
#910
b10000000000000 '
b10000000000000 !
b1101 $
b1101 &
#1000
0"
#1050
b100000000000000 '
b100000000000000 !
b1110 $
b1110 &
#1100
1"
#1200
b1000000000000000 '
b1000000000000000 !
0"
b1111 $
b1111 &
#1300
1"
#1360
b10000000000000000 '
b10000000000000000 !
b10000 $
b10000 &
#1400
0"
#1500
1"
#1530
b100000000000000000 '
b100000000000000000 !
b10001 $
b10001 &
#1600
0"
#1700
1"
#1710
b1000000000000000000 '
b1000000000000000000 !
b10010 $
b10010 &
#1800
0"
#1900
b10000000000000000000 '
b10000000000000000000 !
1"
b10011 $
b10011 &
#2000
0"
#2100
b100000000000000000000 '
b100000000000000000000 !
1"
b10100 $
b10100 &
#2200
0"
#2300
1"
#2310
b1000000000000000000000 '
b1000000000000000000000 !
b10101 $
b10101 &
#2400
0"
#2500
1"
#2530
b10000000000000000000000 '
b10000000000000000000000 !
b10110 $
b10110 &
#2600
0"
#2700
1"
#2760
b100000000000000000000000 '
b100000000000000000000000 !
b10111 $
b10111 &
#2800
0"
#2900
1"
#3000
b1000000000000000000000000 '
b1000000000000000000000000 !
0"
b11000 $
b11000 &
#3100
1"
#3200
0"
#3250
b10000000000000000000000000 '
b10000000000000000000000000 !
b11001 $
b11001 &
#3300
1"
#3400
0"
#3500
1"
#3510
b100000000000000000000000000 '
b100000000000000000000000000 !
b11010 $
b11010 &
#3600
0"
#3700
1"
#3780
b1000000000000000000000000000 '
b1000000000000000000000000000 !
b11011 $
b11011 &
#3800
0"
#3900
1"
#4000
0"
#4060
b10000000000000000000000000000 '
b10000000000000000000000000000 !
b11100 $
b11100 &
#4100
1"
#4200
0"
#4300
1"
#4350
b100000000000000000000000000000 '
b100000000000000000000000000000 !
b11101 $
b11101 &
#4400
0"
#4500
1"
#4600
0"
#4650
b1000000000000000000000000000000 '
b1000000000000000000000000000000 !
b11110 $
b11110 &
#4700
1"
#4800
0"
#4900
1"
#4960
b10000000000000000000000000000000 '
b10000000000000000000000000000000 !
b11111 $
b11111 &
