mux32to1/register.v
module register(clock, enable, in_reg, out_reg);
    input clock, enable;
    input   [31:0] in_reg;
    output reg [31:0] out_reg;

    always@(posedge clock)
            if(enable)
                out_reg <= in_reg;
endmodule

mux32to1/mux32to1.v

module mux32to1(select, R00, R01, R02, R03, R04, 
            R05, R06, R07, R08, R09, R10,
            R11, R12, R13, R14, R15, R16,
            R17, R18, R19, R20, R21, R22,
            R23, R24, R25, R26, R27, R28,
            R29, R30, R31, out_reg);
    
input  [4:0]  select;
input  [31:0] R01, R02, R03, R04, R05, R06, R07, R08;
input  [31:0] R09, R10, R11, R12, R13, R14, R15, R16;
input  [31:0] R17, R18, R19, R20, R21, R22, R23, R24;
input  [31:0] R25, R26, R27, R28, R29, R30, R31, R00; 
     
output reg [31:0]  out_reg;

always @(*) 
    begin
        case(select)
            5'b00000: out_reg = R00;
            5'b00001: out_reg = R01;
            5'b00010: out_reg = R02;
            5'b00011: out_reg = R03;
            5'b00100: out_reg = R04;
            5'b00101: out_reg = R05;
            5'b00110: out_reg = R06;
            5'b00111: out_reg = R07;
            5'b01000: out_reg = R08;
            5'b01001: out_reg = R09;
            5'b01010: out_reg = R10;
            5'b01011: out_reg = R11;
            5'b01100: out_reg = R12;
            5'b01101: out_reg = R13;
            5'b01110: out_reg = R14;
            5'b01111: out_reg = R15;

            5'b10000: out_reg = R16;
            5'b10001: out_reg = R17;
            5'b10010: out_reg = R18;
            5'b10011: out_reg = R19;
            5'b10100: out_reg = R20;
            5'b10101: out_reg = R21;
            5'b10110: out_reg = R22;
            5'b10111: out_reg = R23;
            5'b11000: out_reg = R24;
            5'b11001: out_reg = R25;
            5'b11010: out_reg = R26;
            5'b11011: out_reg = R27;
            5'b11100: out_reg = R28;
            5'b11101: out_reg = R29;
            5'b11110: out_reg = R30;
            5'b11111: out_reg = R31;            
                
            endcase
    end

endmodule

mux32to1/mux32to1_test.v
`include "mux32to1.v"
`include "register.v"

module mux32to1_test;
    
    reg clock, enable;
    reg  [4:0]  select;
     
    reg [31:0]  out_reg;
    reg [31:0] A = 32'b1111; //15
    reg [31:0] B = 32'b1010; //10
    reg [31:0] C = 32'b0000; //00
    reg [31:0] D = 32'b0001; //01
    reg [31:0] E = 32'b0010; //02
    reg [31:0] F = 32'hF000; //2^32
    reg [31:0] G = 32'b0100; //04
    reg [31:0] H = 32'b1011; //11

    wire [31:0] Rout0, Rout1, Rout2, Rout3, Rout4, Rout5, Rout6, Rout7;
    wire [31:0] Rout8, Rout9, Rout10, Rout11, Rout12, Rout13, Rout14, Rout15;
    wire [31:0] Rout16, Rout17, Rout18, Rout19, Rout20, Rout21, Rout22, Rout23; 
    wire [31:0] Rout24, Rout25, Rout26, Rout27, Rout28, Rout29, Rout30, Rout31;
    wire  [31:0] data_out;


    mux32to1 M(select, Rout0, Rout1, Rout2, Rout3, Rout4, Rout5, Rout6, Rout7,
                Rout8, Rout9, Rout10, Rout11, Rout12, Rout13, Rout14, Rout15,
                Rout16, Rout17, Rout18, Rout19, Rout20, Rout21, Rout22, Rout23,
                Rout24, Rout25, Rout26, Rout27, Rout28, Rout29, Rout30, Rout31,
                data_out);

    register R0(clock, 1, A, Rout0);
    register R1(clock, 1, B, Rout1);
    register R2(clock, 1, C, Rout2);
    register R3(clock, 1, D, Rout3);
    register R4(clock, 1, E, Rout4);
    register R5(clock, 1, F, Rout5);
    register R6(clock, 1, G, Rout6);
    // register R7(clock, 1, H, Rout7);

    // register R8(clock, 1, out_reg, Rout8);
    // register R9(clock, 1, out_reg, Rout9);
    // register R10(clock, 1, out_reg, Rout10);
    // register R11(clock, 1, out_reg, Rout11);
    // register R12(clock, 1, out_reg, Rout12);
    // register R13(clock, 1, out_reg, Rout13);
    // register R14(clock, 1, out_reg, Rout14);
    // register R15(clock, 1, out_reg, Rout15);

    // register R16(clock, 1, out_reg, Rout16);
    // register R17(clock, 1, out_reg, Rout17);
    // register R18(clock, 1, out_reg, Rout18);
    // register R19(clock, 1, out_reg, Rout19);
    // register R20(clock, 1, out_reg, Rout20);
    // register R21(clock, 1, out_reg, Rout21);
    // register R22(clock, 1, out_reg, Rout22);
    // register R23(clock, 1, out_reg, Rout23);

    // register R24(clock, 1, out_reg, Rout24);
    // register R25(clock, 1, out_reg, Rout25);
    // register R26(clock, 1, out_reg, Rout26);
    // register R27(clock, 1, out_reg, Rout27);
    // register R28(clock, 1, out_reg, Rout28);
    // register R29(clock, 1, out_reg, Rout29);
    // register R30(clock, 1, out_reg, Rout30);
    // register R31(clock, 1, out_reg, Rout31);


    initial
        begin
            $dumpfile("mux32to1_test.vcd");
            $dumpvars(0, mux32to1_test);

        end
        

    // initial
    //     begin
    //         $display("");
    //         $display("select       data_out_M          R0                  R1                  R2                  R3              time");
    //         $monitor("  %b        %h            %h            %h            %h              %h    %d", select, data_out, Rout0, Rout1, Rout2, Rout3, $time);
    //     end

    initial
        begin
            $display("");
            $display("select       data_out_M            R0               R1               R2               R3               R4               R5               R6");
            $monitor("  %b        %h         %h         %h         %h          %h          %h          %h          %h", select, data_out, Rout0, Rout1, Rout2, Rout3, Rout4, Rout5, Rout6);
        end

    initial begin

#0 select = 5'b00000;         
        #10 select = 5'b00001;          
        #20 select = 5'b00010;          
        #30 select = 5'b00011;          
        #40 select = 5'b00100;                   
        #50 select = 5'b00101;          
        #60 select = 5'b00110;         
        #70 select = 5'b00111;  
        #80 select = 5'b01000;          
        #90 select = 5'b01001;          
        #100 select = 5'b01010;         

        #110 select = 5'b01011;          
        #120 select = 5'b01100;          
        #130 select = 5'b01101;          
        #140 select = 5'b01110;          
        #150 select = 5'b01111;         
        #160 select = 5'b10000;        
        #170 select = 5'b10001;       
        #180 select = 5'b10010;      
        #190 select = 5'b10011;     
        #200 select = 5'b10100;    

        #210 select = 5'b10101;   
        #220 select = 5'b10110;  
        #230 select = 5'b10111; 
        #240 select = 5'b11000;
        #250 select = 5'b11001;
        #260 select = 5'b11010;
        #270 select = 5'b11011;
        #280 select = 5'b11100;
        #290 select = 5'b11101;
        #300 select = 5'b11110;
        #310 select = 5'b11111;
       





        // // #0 enable =0;
        // #0 select = 5'b00000;         
        // // #0 out_reg = 32'b0000_0000_0000_0000_0000_0000_0000_0001;

        // // #10 enable =1;
        // // #20 enable =0;
        // #30 select = 5'b00001;          
        // // #30 out_reg = 32'b0000_0000_0000_0000_0000_0000_0000_0010;
        
        // // #40 enable =1;
        // // #50 enable =0;
        // #60 select = 5'b00010;          
        // // #60 out_reg = 32'b0000_0000_0000_0000_0000_0000_0000_0100;
        
        // // #70 enable =1;
        // // #80 enable =0;
        // #90 select = 5'b00011;          
        // // #90 out_reg = 32'b0000_0000_0000_0000_0000_0000_0000_1000;
        
        // // #100 enable =1;
        // // #110 enable =0;
        // #120 select = 5'b00100;          
        // // #120 out_reg = 32'b0000_0000_0000_0000_0000_0000_0001_0000;

        // // #130 enable =1;
        // // #140 enable =0;
        // #150 select = 5'b00101;          
        // // #150 out_reg = 32'b0000_0000_0000_0000_0000_0000_0010_0000;

        // // #160 enable =1;
        // // #170 enable =0;
        // #180 select = 5'b00110;         
        // // #180 out_reg = 32'b0000_0000_0000_0000_0000_0000_0100_0000;

        // // #190 enable =1;
        // // #200 enable =0;
        // #210 select = 5'b00111;  
        // // #210 out_reg = 32'b0000_0000_0000_0000_0000_0000_1000_0000;

        // // #220 enable =1;
        // // #230 enable =0;
        // #240 select = 5'b01000;          
        // // #240 out_reg = 32'b0000_0000_0000_0000_0000_0001_0000_0000;

        // #90 select = 5'b01001;          
        // #90 out_reg = 32'b0000_0000_0000_0000_0000_0010_0000_0000;

        // #100 select = 5'b01010;         
        // #100 out_reg = 32'b0000_0000_0000_0000_0000_0100_0000_0000;

        // #110 select = 5'b01011;          
        // #110 out_reg = 32'b0000_0000_0000_0000_0000_1000_0000_0000;

        // #120 select = 5'b01100;          
        // #120 out_reg = 32'b0000_0000_0000_0000_0001_0000_0000_0000;

        // #130 select = 5'b01101;          
        // #130 out_reg = 32'b0000_0000_0000_0000_0010_0000_0000_0000;

        // #140 select = 5'b01110;          
        // #140 out_reg = 32'b0000_0000_0000_0000_0100_0000_0000_0000;

        // #150 select = 5'b01111;         
        // #150 out_reg = 32'b0000_0000_0000_0000_1000_0000_0000_0000;

        // #160 select = 5'b10000;        
        // #160 out_reg = 32'b0000_0000_0000_0001_0000_0000_0000_0000;

        // #170 select = 5'b10001;       
        // #170 out_reg = 32'b0000_0000_0000_0010_0000_0000_0000_0000;

        // #180 select = 5'b10010;      
        // #180 out_reg = 32'b0000_0000_0000_0100_0000_0000_0000_0000;

        // #190 select = 5'b10011;     
        // #190 out_reg = 32'b0000_0000_0000_1000_0000_0000_0000_0000;

        // #200 select = 5'b10100;    
        // #200 out_reg = 32'b0000_0000_0001_0000_0000_0000_0000_0000;

        // #210 select = 5'b10101;   
        // #210 out_reg = 32'b0000_0000_0010_0000_0000_0000_0000_0000;

        // #220 select = 5'b10110;  
        // #220 out_reg = 32'b0000_0000_0100_0000_0000_0000_0000_0000;

        // #230 select = 5'b10111; 
        // #230 out_reg = 32'b0000_0000_1000_0000_0000_0000_0000_0000;

        // #240 select = 5'b11000;
        // #240 out_reg = 32'b0000_0001_0000_0000_0000_0000_0000_0000;

        // #250 select = 5'b11001;
        // #250 out_reg = 32'b0000_0010_0000_0000_0000_0000_0000_0000;

        // #260 select = 5'b11010;
        // #260 out_reg = 32'b0000_0100_0000_0000_0000_0000_0000_0000;

        // #270 select = 5'b11011;
        // #270 out_reg = 32'b0000_1000_0000_0000_0000_0000_0000_0000;

        // #280 select = 5'b11100;
        // #280 out_reg = 32'b0001_0000_0000_0000_0000_0000_0000_0000;

        // #290 select = 5'b11101;
        // #290 out_reg = 32'b0010_0000_0000_0000_0000_0000_0000_0000;

        // #300 select = 5'b11110;
        // #300 out_reg = 32'b0100_0000_0000_0000_0000_0000_0000_0000;

        // #310 select = 5'b11111;
        // #310 out_reg = 32'b1000_0000_0000_0000_0000_0000_0000_0000;

    end

    initial begin
        clock = 1'b0;
        forever #10 clock = ~clock;
    end

    initial #5000 $finish;

endmodule

mux32to1/mux32to1_test.vcd
$date
	Sat Mar 11 06:48:49 2023
$end
$version
	Icarus Verilog
$end
$timescale
	1s
$end
$scope module mux32to1_test $end
$var wire 32 ! Rout0 [31:0] $end
$var wire 32 " Rout1 [31:0] $end
$var wire 32 # Rout10 [31:0] $end
$var wire 32 $ Rout11 [31:0] $end
$var wire 32 % Rout12 [31:0] $end
$var wire 32 & Rout13 [31:0] $end
$var wire 32 ' Rout14 [31:0] $end
$var wire 32 ( Rout15 [31:0] $end
$var wire 32 ) Rout16 [31:0] $end
$var wire 32 * Rout17 [31:0] $end
$var wire 32 + Rout18 [31:0] $end
$var wire 32 , Rout19 [31:0] $end
$var wire 32 - Rout2 [31:0] $end
$var wire 32 . Rout20 [31:0] $end
$var wire 32 / Rout21 [31:0] $end
$var wire 32 0 Rout22 [31:0] $end
$var wire 32 1 Rout23 [31:0] $end
$var wire 32 2 Rout24 [31:0] $end
$var wire 32 3 Rout25 [31:0] $end
$var wire 32 4 Rout26 [31:0] $end
$var wire 32 5 Rout27 [31:0] $end
$var wire 32 6 Rout28 [31:0] $end
$var wire 32 7 Rout29 [31:0] $end
$var wire 32 8 Rout3 [31:0] $end
$var wire 32 9 Rout30 [31:0] $end
$var wire 32 : Rout31 [31:0] $end
$var wire 32 ; Rout4 [31:0] $end
$var wire 32 < Rout5 [31:0] $end
$var wire 32 = Rout6 [31:0] $end
$var wire 32 > Rout7 [31:0] $end
$var wire 32 ? Rout8 [31:0] $end
$var wire 32 @ Rout9 [31:0] $end
$var wire 32 A data_out [31:0] $end
$var reg 32 B A [31:0] $end
$var reg 32 C B [31:0] $end
$var reg 32 D C [31:0] $end
$var reg 32 E D [31:0] $end
$var reg 32 F E [31:0] $end
$var reg 32 G F [31:0] $end
$var reg 32 H G [31:0] $end
$var reg 32 I H [31:0] $end
$var reg 1 J clock $end
$var reg 5 K select [4:0] $end
$scope module M $end
$var wire 32 L R00 [31:0] $end
$var wire 32 M R01 [31:0] $end
$var wire 32 N R02 [31:0] $end
$var wire 32 O R03 [31:0] $end
$var wire 32 P R04 [31:0] $end
$var wire 32 Q R05 [31:0] $end
$var wire 32 R R06 [31:0] $end
$var wire 32 S R07 [31:0] $end
$var wire 32 T R08 [31:0] $end
$var wire 32 U R09 [31:0] $end
$var wire 32 V R10 [31:0] $end
$var wire 32 W R11 [31:0] $end
$var wire 32 X R12 [31:0] $end
$var wire 32 Y R13 [31:0] $end
$var wire 32 Z R14 [31:0] $end
$var wire 32 [ R15 [31:0] $end
$var wire 32 \ R16 [31:0] $end
$var wire 32 ] R17 [31:0] $end
$var wire 32 ^ R18 [31:0] $end
$var wire 32 _ R19 [31:0] $end
$var wire 32 ` R20 [31:0] $end
$var wire 32 a R21 [31:0] $end
$var wire 32 b R22 [31:0] $end
$var wire 32 c R23 [31:0] $end
$var wire 32 d R24 [31:0] $end
$var wire 32 e R25 [31:0] $end
$var wire 32 f R26 [31:0] $end
$var wire 32 g R27 [31:0] $end
$var wire 32 h R28 [31:0] $end
$var wire 32 i R29 [31:0] $end
$var wire 32 j R30 [31:0] $end
$var wire 32 k R31 [31:0] $end
$var wire 5 l select [4:0] $end
$var reg 32 m out_reg [31:0] $end
$upscope $end
$scope module R0 $end
$var wire 1 n clock $end
$var wire 1 o enable $end
$var wire 32 p in_reg [31:0] $end
$var reg 32 q out_reg [31:0] $end
$upscope $end
$scope module R1 $end
$var wire 1 n clock $end
$var wire 1 r enable $end
$var wire 32 s in_reg [31:0] $end
$var reg 32 t out_reg [31:0] $end
$upscope $end
$scope module R2 $end
$var wire 1 n clock $end
$var wire 1 u enable $end
$var wire 32 v in_reg [31:0] $end
$var reg 32 w out_reg [31:0] $end
$upscope $end
$scope module R3 $end
$var wire 1 n clock $end
$var wire 1 x enable $end
$var wire 32 y in_reg [31:0] $end
$var reg 32 z out_reg [31:0] $end
$upscope $end
$scope module R4 $end
$var wire 1 n clock $end
$var wire 1 { enable $end
$var wire 32 | in_reg [31:0] $end
$var reg 32 } out_reg [31:0] $end
$upscope $end
$scope module R5 $end
$var wire 1 n clock $end
$var wire 1 ~ enable $end
$var wire 32 !" in_reg [31:0] $end
$var reg 32 "" out_reg [31:0] $end
$upscope $end
$scope module R6 $end
$var wire 1 n clock $end
$var wire 1 #" enable $end
$var wire 32 $" in_reg [31:0] $end
$var reg 32 %" out_reg [31:0] $end
$upscope $end
$upscope $end
$enddefinitions $end
#0
$dumpvars
bx %"
b100 $"
1#"
bx ""
b1111000000000000 !"
1~
bx }
b10 |
1{
bx z
b1 y
1x
bx w
b0 v
1u
bx t
b1010 s
1r
bx q
b1111 p
1o
0n
bx m
b0 l
bz k
bz j
bz i
bz h
bz g
bz f
bz e
bz d
bz c
bz b
bz a
bz `
bz _
bz ^
bz ]
bz \
bz [
bz Z
bz Y
bz X
bz W
bz V
bz U
bz T
bz S
bx R
bx Q
bx P
bx O
bx N
bx M
bx L
b0 K
0J
b1011 I
b100 H
b1111000000000000 G
b10 F
b1 E
b0 D
b1010 C
b1111 B
bx A
bz @
bz ?
bz >
bx =
bx <
bx ;
bz :
bz 9
bx 8
bz 7
bz 6
bz 5
bz 4
bz 3
bz 2
bz 1
bz 0
bz /
bz .
bx -
bz ,
bz +
bz *
bz )
bz (
bz '
bz &
bz %
bz $
bz #
bx "
bx !
$end
#10
b1010 m
b1010 A
b1111 q
b1111 !
b1111 L
b1010 t
b1010 "
b1010 M
b0 w
b0 -
b0 N
b1 z
b1 8
b1 O
b10 }
b10 ;
b10 P
b1111000000000000 ""
b1111000000000000 <
b1111000000000000 Q
b100 %"
b100 =
b100 R
b1 K
b1 l
1J
1n
#20
0J
0n
#30
b0 m
b0 A
1J
1n
b10 K
b10 l
#40
0J
0n
#50
1J
1n
#60
b1 m
b1 A
0J
0n
b11 K
b11 l
#70
1J
1n
#80
0J
0n
#90
1J
1n
#100
b10 m
b10 A
0J
0n
b100 K
b100 l
#110
1J
1n
#120
0J
0n
#130
1J
1n
#140
0J
0n
#150
b1111000000000000 m
b1111000000000000 A
1J
1n
b101 K
b101 l
#160
0J
0n
#170
1J
1n
#180
0J
0n
#190
1J
1n
#200
0J
0n
#210
b100 m
b100 A
1J
1n
b110 K
b110 l
#220
0J
0n
#230
1J
1n
#240
0J
0n
#250
1J
1n
#260
0J
0n
#270
1J
1n
#280
bz m
bz A
0J
0n
b111 K
b111 l
#290
1J
1n
#300
0J
0n
#310
1J
1n
#320
0J
0n
#330
1J
1n
#340
0J
0n
#350
1J
1n
#360
0J
0n
b1000 K
b1000 l
#370
1J
1n
#380
0J
0n
#390
1J
1n
#400
0J
0n
#410
1J
1n
#420
0J
0n
#430
1J
1n
#440
0J
0n
#450
1J
1n
b1001 K
b1001 l
#460
0J
0n
#470
1J
1n
#480
0J
0n
#490
1J
1n
#500
0J
0n
#510
1J
1n
#520
0J
0n
#530
1J
1n
#540
0J
0n
#550
1J
1n
b1010 K
b1010 l
#560
0J
0n
#570
1J
1n
#580
0J
0n
#590
1J
1n
#600
0J
0n
#610
1J
1n
#620
0J
0n
#630
1J
1n
#640
0J
0n
#650
1J
1n
#660
0J
0n
b1011 K
b1011 l
#670
1J
1n
#680
0J
0n
#690
1J
1n
#700
0J
0n
#710
1J
1n
#720
0J
0n
#730
1J
1n
#740
0J
0n
#750
1J
1n
#760
0J
0n
#770
1J
1n
#780
0J
0n
b1100 K
b1100 l
#790
1J
1n
#800
0J
0n
#810
1J
1n
#820
0J
0n
#830
1J
1n
#840
0J
0n
#850
1J
1n
#860
0J
0n
#870
1J
1n
#880
0J
0n
#890
1J
1n
#900
0J
0n
#910
1J
1n
b1101 K
b1101 l
#920
0J
0n
#930
1J
1n
#940
0J
0n
#950
1J
1n
#960
0J
0n
#970
1J
1n
#980
0J
0n
#990
1J
1n
#1000
0J
0n
#1010
1J
1n
#1020
0J
0n
#1030
1J
1n
#1040
0J
0n
#1050
1J
1n
b1110 K
b1110 l
#1060
0J
0n
#1070
1J
1n
#1080
0J
0n
#1090
1J
1n
#1100
0J
0n
#1110
1J
1n
#1120
0J
0n
#1130
1J
1n
#1140
0J
0n
#1150
1J
1n
#1160
0J
0n
#1170
1J
1n
#1180
0J
0n
#1190
1J
1n
#1200
0J
0n
b1111 K
b1111 l
#1210
1J
1n
#1220
0J
0n
#1230
1J
1n
#1240
0J
0n
#1250
1J
1n
#1260
0J
0n
#1270
1J
1n
#1280
0J
0n
#1290
1J
1n
#1300
0J
0n
#1310
1J
1n
#1320
0J
0n
#1330
1J
1n
#1340
0J
0n
#1350
1J
1n
#1360
0J
0n
b10000 K
b10000 l
#1370
1J
1n
#1380
0J
0n
#1390
1J
1n
#1400
0J
0n
#1410
1J
1n
#1420
0J
0n
#1430
1J
1n
#1440
0J
0n
#1450
1J
1n
#1460
0J
0n
#1470
1J
1n
#1480
0J
0n
#1490
1J
1n
#1500
0J
0n
#1510
1J
1n
#1520
0J
0n
#1530
1J
1n
b10001 K
b10001 l
#1540
0J
0n
#1550
1J
1n
#1560
0J
0n
#1570
1J
1n
#1580
0J
0n
#1590
1J
1n
#1600
0J
0n
#1610
1J
1n
#1620
0J
0n
#1630
1J
1n
#1640
0J
0n
#1650
1J
1n
#1660
0J
0n
#1670
1J
1n
#1680
0J
0n
#1690
1J
1n
#1700
0J
0n
#1710
1J
1n
b10010 K
b10010 l
#1720
0J
0n
#1730
1J
1n
#1740
0J
0n
#1750
1J
1n
#1760
0J
0n
#1770
1J
1n
#1780
0J
0n
#1790
1J
1n
#1800
0J
0n
#1810
1J
1n
#1820
0J
0n
#1830
1J
1n
#1840
0J
0n
#1850
1J
1n
#1860
0J
0n
#1870
1J
1n
#1880
0J
0n
#1890
1J
1n
#1900
0J
0n
b10011 K
b10011 l
#1910
1J
1n
#1920
0J
0n
#1930
1J
1n
#1940
0J
0n
#1950
1J
1n
#1960
0J
0n
#1970
1J
1n
#1980
0J
0n
#1990
1J
1n
#2000
0J
0n
#2010
1J
1n
#2020
0J
0n
#2030
1J
1n
#2040
0J
0n
#2050
1J
1n
#2060
0J
0n
#2070
1J
1n
#2080
0J
0n
#2090
1J
1n
#2100
0J
0n
b10100 K
b10100 l
#2110
1J
1n
#2120
0J
0n
#2130
1J
1n
#2140
0J
0n
#2150
1J
1n
#2160
0J
0n
#2170
1J
1n
#2180
0J
0n
#2190
1J
1n
#2200
0J
0n
#2210
1J
1n
#2220
0J
0n
#2230
1J
1n
#2240
0J
0n
#2250
1J
1n
#2260
0J
0n
#2270
1J
1n
#2280
0J
0n
#2290
1J
1n
#2300
0J
0n
#2310
1J
1n
b10101 K
b10101 l
#2320
0J
0n
#2330
1J
1n
#2340
0J
0n
#2350
1J
1n
#2360
0J
0n
#2370
1J
1n
#2380
0J
0n
#2390
1J
1n
#2400
0J
0n
#2410
1J
1n
#2420
0J
0n
#2430
1J
1n
#2440
0J
0n
#2450
1J
1n
#2460
0J
0n
#2470
1J
1n
#2480
0J
0n
#2490
1J
1n
#2500
0J
0n
#2510
1J
1n
#2520
0J
0n
#2530
1J
1n
b10110 K
b10110 l
#2540
0J
0n
#2550
1J
1n
#2560
0J
0n
#2570
1J
1n
#2580
0J
0n
#2590
1J
1n
#2600
0J
0n
#2610
1J
1n
#2620
0J
0n
#2630
1J
1n
#2640
0J
0n
#2650
1J
1n
#2660
0J
0n
#2670
1J
1n
#2680
0J
0n
#2690
1J
1n
#2700
0J
0n
#2710
1J
1n
#2720
0J
0n
#2730
1J
1n
#2740
0J
0n
#2750
1J
1n
#2760
0J
0n
b10111 K
b10111 l
#2770
1J
1n
#2780
0J
0n
#2790
1J
1n
#2800
0J
0n
#2810
1J
1n
#2820
0J
0n
#2830
1J
1n
#2840
0J
0n
#2850
1J
1n
#2860
0J
0n
#2870
1J
1n
#2880
0J
0n
#2890
1J
1n
#2900
0J
0n
#2910
1J
1n
#2920
0J
0n
#2930
1J
1n
#2940
0J
0n
#2950
1J
1n
#2960
0J
0n
#2970
1J
1n
#2980
0J
0n
#2990
1J
1n
#3000
0J
0n
b11000 K
b11000 l
#3010
1J
1n
#3020
0J
0n
#3030
1J
1n
#3040
0J
0n
#3050
1J
1n
#3060
0J
0n
#3070
1J
1n
#3080
0J
0n
#3090
1J
1n
#3100
0J
0n
#3110
1J
1n
#3120
0J
0n
#3130
1J
1n
#3140
0J
0n
#3150
1J
1n
#3160
0J
0n
#3170
1J
1n
#3180
0J
0n
#3190
1J
1n
#3200
0J
0n
#3210
1J
1n
#3220
0J
0n
#3230
1J
1n
#3240
0J
0n
#3250
1J
1n
b11001 K
b11001 l
#3260
0J
0n
#3270
1J
1n
#3280
0J
0n
#3290
1J
1n
#3300
0J
0n
#3310
1J
1n
#3320
0J
0n
#3330
1J
1n
#3340
0J
0n
#3350
1J
1n
#3360
0J
0n
#3370
1J
1n
#3380
0J
0n
#3390
1J
1n
#3400
0J
0n
#3410
1J
1n
#3420
0J
0n
#3430
1J
1n
#3440
0J
0n
#3450
1J
1n
#3460
0J
0n
#3470
1J
1n
#3480
0J
0n
#3490
1J
1n
#3500
0J
0n
#3510
1J
1n
b11010 K
b11010 l
#3520
0J
0n
#3530
1J
1n
#3540
0J
0n
#3550
1J
1n
#3560
0J
0n
#3570
1J
1n
#3580
0J
0n
#3590
1J
1n
#3600
0J
0n
#3610
1J
1n
#3620
0J
0n
#3630
1J
1n
#3640
0J
0n
#3650
1J
1n
#3660
0J
0n
#3670
1J
1n
#3680
0J
0n
#3690
1J
1n
#3700
0J
0n
#3710
1J
1n
#3720
0J
0n
#3730
1J
1n
#3740
0J
0n
#3750
1J
1n
#3760
0J
0n
#3770
1J
1n
#3780
0J
0n
b11011 K
b11011 l
#3790
1J
1n
#3800
0J
0n
#3810
1J
1n
#3820
0J
0n
#3830
1J
1n
#3840
0J
0n
#3850
1J
1n
#3860
0J
0n
#3870
1J
1n
#3880
0J
0n
#3890
1J
1n
#3900
0J
0n
#3910
1J
1n
#3920
0J
0n
#3930
1J
1n
#3940
0J
0n
#3950
1J
1n
#3960
0J
0n
#3970
1J
1n
#3980
0J
0n
#3990
1J
1n
#4000
0J
0n
#4010
1J
1n
#4020
0J
0n
#4030
1J
1n
#4040
0J
0n
#4050
1J
1n
#4060
0J
0n
b11100 K
b11100 l
#4070
1J
1n
#4080
0J
0n
#4090
1J
1n
#4100
0J
0n
#4110
1J
1n
#4120
0J
0n
#4130
1J
1n
#4140
0J
0n
#4150
1J
1n
#4160
0J
0n
#4170
1J
1n
#4180
0J
0n
#4190
1J
1n
#4200
0J
0n
#4210
1J
1n
#4220
0J
0n
#4230
1J
1n
#4240
0J
0n
#4250
1J
1n
#4260
0J
0n
#4270
1J
1n
#4280
0J
0n
#4290
1J
1n
#4300
0J
0n
#4310
1J
1n
#4320
0J
0n
#4330
1J
1n
#4340
0J
0n
#4350
1J
1n
b11101 K
b11101 l
#4360
0J
0n
#4370
1J
1n
#4380
0J
0n
#4390
1J
1n
#4400
0J
0n
#4410
1J
1n
#4420
0J
0n
#4430
1J
1n
#4440
0J
0n
#4450
1J
1n
#4460
0J
0n
#4470
1J
1n
#4480
0J
0n
#4490
1J
1n
#4500
0J
0n
#4510
1J
1n
#4520
0J
0n
#4530
1J
1n
#4540
0J
0n
#4550
1J
1n
#4560
0J
0n
#4570
1J
1n
#4580
0J
0n
#4590
1J
1n
#4600
0J
0n
#4610
1J
1n
#4620
0J
0n
#4630
1J
1n
#4640
0J
0n
#4650
1J
1n
b11110 K
b11110 l
#4660
0J
0n
#4670
1J
1n
#4680
0J
0n
#4690
1J
1n
#4700
0J
0n
#4710
1J
1n
#4720
0J
0n
#4730
1J
1n
#4740
0J
0n
#4750
1J
1n
#4760
0J
0n
#4770
1J
1n
#4780
0J
0n
#4790
1J
1n
#4800
0J
0n
#4810
1J
1n
#4820
0J
0n
#4830
1J
1n
#4840
0J
0n
#4850
1J
1n
#4860
0J
0n
#4870
1J
1n
#4880
0J
0n
#4890
1J
1n
#4900
0J
0n
#4910
1J
1n
#4920
0J
0n
#4930
1J
1n
#4940
0J
0n
#4950
1J
1n
#4960
0J
0n
b11111 K
b11111 l
